metaflow_extensions/tensorflow/plugins/mfextinit_tensorflow.py
metaflow_extensions/tensorflow/plugins/tensorflow_decorator.py
metaflow_tensorflow-0.0.4.dist-info/LICENSE
metaflow_tensorflow-0.0.4.dist-info/METADATA
metaflow_tensorflow-0.0.4.dist-info/WHEEL
metaflow_tensorflow-0.0.4.dist-info/top_level.txt
metaflow_tensorflow-0.0.4.dist-info/RECORD
