Metadata-Version: 2.1
Name: metaflow-tensorflow
Version: 0.0.4
Summary: An EXPERIMENTAL TensorFlow decorator for Metaflow
Author: Eddie Mattia
Author-email: eddie@outerbounds.co
License-File: LICENSE
